{
  "schemaVersion": 1,
  "updatedAt": "2026-07-10",
  "minimumAppVersion": "1.0.0",
  "sources": [
    {
      "id": "mangakatana_json",
      "name": "MangaKatana JSON",
      "version": 3,
      "language": "en",
      "kind": "declarative-html",
      "url": "https://raw.githubusercontent.com/lukqo/Yomuhon-Sources/main/sources/mangakatana.json",
      "enabled": true,
      "experimental": true,
      "status": "testing",
      "allowedDomains": [
        "mangakatana.com",
        "i.mkklcdnv6.com",
        "i.mkklcdnv6tempv2.com"
      ],
      "notes": "Declarative adapter under continuous live verification. It remains inactive in the app until the full diagnostic passes."
    },
    {
      "id": "mangapill_json",
      "name": "MangaPill JSON",
      "version": 1,
      "language": "en",
      "kind": "declarative-html",
      "url": "https://raw.githubusercontent.com/lukqo/Yomuhon-Sources/main/sources/mangapill.json",
      "enabled": true,
      "experimental": true,
      "status": "testing",
      "allowedDomains": [
        "mangapill.com",
        "cdn.mangapill.com"
      ],
      "notes": "Discovered remotely but never enabled by default. Yomuhon activates it only after search, chapters and pages pass the local diagnostic."
    }
  ]
}
