{
  "schemaVersion": 1,
  "updatedAt": "2026-07-12",
  "minimumAppVersion": "1.0.0",
  "sources": [
    {
      "id": "mangadex",
      "name": "MangaDex",
      "version": 2,
      "language": "multi",
      "kind": "declarative-json-api",
      "url": "https://raw.githubusercontent.com/lukqo/Yomuhon-Sources/main/sources/mangadex.json",
      "enabled": true,
      "experimental": false,
      "status": "stable",
      "allowedDomains": [
        "api.mangadex.org",
        "uploads.mangadex.org"
      ],
      "notes": "JSON API source with response-driven pagination executed by Yomuhon's generic declarative runtime."
    },
    {
      "id": "mangakatana_json",
      "name": "MangaKatana JSON",
      "version": 7,
      "language": "en",
      "kind": "declarative-html",
      "url": "https://raw.githubusercontent.com/lukqo/Yomuhon-Sources/main/sources/mangakatana.json",
      "enabled": true,
      "experimental": true,
      "status": "testing",
      "allowedDomains": [
        "mangakatana.com",
        "i.mkklcdnv6tempv2.com",
        "i.mkklcdnv6.com"
      ],
      "notes": "Declarative HTML source. v7 keeps Discover/genres and fixes reader extraction for plain and JavaScript-escaped page image URLs."
    },
    {
      "id": "mangapill_json",
      "name": "MangaPill JSON",
      "version": 3,
      "language": "en",
      "kind": "declarative-html",
      "url": "https://raw.githubusercontent.com/lukqo/Yomuhon-Sources/main/sources/mangapill.json",
      "enabled": true,
      "experimental": true,
      "status": "testing",
      "allowedDomains": [
        "mangapill.com",
        "cdn.mangapill.com",
        "cdn.readdetectiveconan.com"
      ],
      "notes": "Declarative HTML source."
    }
  ]
}
